plan_lint/__init__.py
plan_lint/__main__.py
plan_lint/cli.py
plan_lint/core.py
plan_lint/loader.py
plan_lint/opa.py
plan_lint/types.py
plan_lint/examples/policy.yaml
plan_lint/examples/price_drop.json
plan_lint/reporters/__init__.py
plan_lint/reporters/cli.py
plan_lint/reporters/json.py
plan_lint/rules/__init__.py
plan_lint/rules/deny_sql_write.py
plan_lint/rules/no_raw_secret.py
plan_lint/schemas/plan.schema.json
plan_lint-0.0.3.dist-info/METADATA
plan_lint-0.0.3.dist-info/WHEEL
plan_lint-0.0.3.dist-info/entry_points.txt
plan_lint-0.0.3.dist-info/licenses/LICENSE
plan_lint-0.0.3.dist-info/RECORD
