Metadata-Version: 2.4
Name: plan-lint
Version: 0.0.3
Summary: plan-linter is a static analysis toolkit for LLM agent plans
Project-URL: Homepage, https://github.com/cirbuk/plan-lint
Project-URL: Bug Tracker, https://github.com/cirbuk/plan-lint/issues
Project-URL: Documentation, https://cirbuk.github.io/plan-lint/
Project-URL: Source Code, https://github.com/cirbuk/plan-lint
Project-URL: Changelog, https://github.com/cirbuk/plan-lint/blob/main/CHANGELOG.md
Project-URL: Repository, https://github.com/cirbuk/plan-lint.git
Author: Plan-Linter Contributors
License: Apache-2.0
License-File: LICENSE
Keywords: ai,linter,llm,security,static-analysis
Classifier: Development Status :: 3 - Alpha
Classifier: Intended Audience :: Developers
Classifier: License :: OSI Approved :: Apache Software License
Classifier: Programming Language :: Python :: 3
Classifier: Programming Language :: Python :: 3.11
Classifier: Programming Language :: Python :: 3.12
Classifier: Topic :: Software Development :: Libraries :: Python Modules
Classifier: Topic :: Software Development :: Quality Assurance
Requires-Python: >=3.11
Requires-Dist: jsonschema>=4.0.0
Requires-Dist: pydantic>=2.0.0
Requires-Dist: pyyaml>=6.0.0
Requires-Dist: rich>=13.0.0
Requires-Dist: typer>=0.9.0
Provides-Extra: dev
Requires-Dist: black>=23.0.0; extra == 'dev'
Requires-Dist: isort>=5.0.0; extra == 'dev'
Requires-Dist: mypy>=1.0.0; extra == 'dev'
Requires-Dist: pre-commit>=3.0.0; extra == 'dev'
Requires-Dist: pytest-cov>=4.0.0; extra == 'dev'
Requires-Dist: pytest>=7.0.0; extra == 'dev'
Requires-Dist: ruff>=0.1.0; extra == 'dev'
Provides-Extra: docs
Requires-Dist: mike>=1.1.0; extra == 'docs'
Requires-Dist: mkdocs-git-revision-date-localized-plugin>=1.2.0; extra == 'docs'
Requires-Dist: mkdocs-material>=9.0.0; extra == 'docs'
Requires-Dist: mkdocstrings-python>=1.2.0; extra == 'docs'
Requires-Dist: mkdocstrings>=0.23.0; extra == 'docs'
